[
    {
        "cardid": "+i25Cjlo4kGSGlvmtEBNLA==",
        "sequence": 1,
        "ruling": "- You can't activate [[D.D. Designator]] if you have no cards in your hand, or if [[D.D. Designator]] is the only card in your hand."
    },
    {
        "cardid": "+i25Cjlo4kGSGlvmtEBNLA==",
        "sequence": 2,
        "ruling": "- If you have your opponent's card in your hand because of [[Exchange]], you can remove it from play if you name a card your opponent doesn't have in his hand."
    },
    {
        "cardid": "+i25Cjlo4kGSGlvmtEBNLA==",
        "sequence": 3,
        "ruling": "- You declare the card name when you activate [[D.D. Designator]]."
    },
    {
        "cardid": "+i25Cjlo4kGSGlvmtEBNLA==",
        "sequence": 4,
        "ruling": "- If your opponent has no cards in his hand when [[D.D. Designator]] resolves, the effect of [[D.D. Designator]] is negated."
    },
    {
        "cardid": "+i25Cjlo4kGSGlvmtEBNLA==",
        "sequence": 5,
        "ruling": "- You can't activate [[D.D. Designator]] when your opponent has no cards in his hand."
    },
    {
        "cardid": "+i25Cjlo4kGSGlvmtEBNLA==",
        "sequence": 6,
        "ruling": "- If you activate [[D.D. Designator]] and your opponent has 2 copies of the same card in their hand, you (the player who activated [[D.D. Designator]]) select which of the 2 cards is removed from play."
    }
]