[
    {
        "cardid": "eVAOrnyaYESR0zCg5kqs3g==",
        "sequence": 1,
        "ruling": "- You must show your chosen card to your opponent to verify that it is a Spell Card."
    },
    {
        "cardid": "eVAOrnyaYESR0zCg5kqs3g==",
        "sequence": 2,
        "ruling": "- You can select a Field Spell Card but you must Set it in your Field Card Zone."
    },
    {
        "cardid": "eVAOrnyaYESR0zCg5kqs3g==",
        "sequence": 3,
        "ruling": "- *You cannot use that Spell Card this turn* means that you cannot activate it, and you cannot use it to pay a cost for Summoning [[Anteatereatingant]] or for the effect of a card like [[Emergency Provisions]] or [[Elemental Hero Tempest]]."
    },
    {
        "cardid": "eVAOrnyaYESR0zCg5kqs3g==",
        "sequence": 4,
        "ruling": "- If you get a Spell Card with [[Ancient Gear Drill]] and then return it to your hand with [[Giant Trunade]], restrictions no longer apply so you can use it as normal."
    }
]